opentrons_sila2_server/__init__.py
opentrons_sila2_server/__main__.py
opentrons_sila2_server/base.py
opentrons_sila2_server/py.typed
opentrons_sila2_server/server.py
opentrons_sila2_server/feature_implementations/__init__.py
opentrons_sila2_server/feature_implementations/labware_impl.py
opentrons_sila2_server/feature_implementations/sessionmanagement_impl.py
opentrons_sila2_server/generated/__init__.py
opentrons_sila2_server/generated/client.py
opentrons_sila2_server/generated/labware/Labware.proto
opentrons_sila2_server/generated/labware/Labware.sila.xml
opentrons_sila2_server/generated/labware/__init__.py
opentrons_sila2_server/generated/labware/labware_base.py
opentrons_sila2_server/generated/labware/labware_client.py
opentrons_sila2_server/generated/labware/labware_errors.py
opentrons_sila2_server/generated/labware/labware_feature.py
opentrons_sila2_server/generated/labware/labware_types.py
opentrons_sila2_server/generated/sessionmanagement/SessionManagement.proto
opentrons_sila2_server/generated/sessionmanagement/SessionManagement.sila.xml
opentrons_sila2_server/generated/sessionmanagement/__init__.py
opentrons_sila2_server/generated/sessionmanagement/sessionmanagement_base.py
opentrons_sila2_server/generated/sessionmanagement/sessionmanagement_client.py
opentrons_sila2_server/generated/sessionmanagement/sessionmanagement_errors.py
opentrons_sila2_server/generated/sessionmanagement/sessionmanagement_feature.py
opentrons_sila2_server/generated/sessionmanagement/sessionmanagement_types.py
opentrons_sila2_server/labware/__init__.py
opentrons_sila2_server/labware/labware_wrapper.py
opentrons_sila2_server-0.2.13.dist-info/METADATA
opentrons_sila2_server-0.2.13.dist-info/WHEEL
opentrons_sila2_server-0.2.13.dist-info/top_level.txt
opentrons_sila2_server-0.2.13.dist-info/RECORD
